qrisp/__init__.py
qrisp/default_backend.py
qrisp/alg_primitives/__init__.py
qrisp/alg_primitives/amplitude_amplification.py
qrisp/alg_primitives/dicke_state_prep.py
qrisp/alg_primitives/iterable_processing.py
qrisp/alg_primitives/iterative_qae.py
qrisp/alg_primitives/iterative_qpe.py
qrisp/alg_primitives/lcu.py
qrisp/alg_primitives/qae.py
qrisp/alg_primitives/qft.py
qrisp/alg_primitives/qpe.py
qrisp/alg_primitives/reflection.py
qrisp/alg_primitives/switch_case.py
qrisp/alg_primitives/arithmetic/SBP_arithmetic.py
qrisp/alg_primitives/arithmetic/__init__.py
qrisp/alg_primitives/arithmetic/arithmetic_tools.py
qrisp/alg_primitives/arithmetic/comparisons.py
qrisp/alg_primitives/arithmetic/matrix_multiplication.py
qrisp/alg_primitives/arithmetic/poly_tools.py
qrisp/alg_primitives/arithmetic/qcla_adder.py
qrisp/alg_primitives/arithmetic/ripple_division.py
qrisp/alg_primitives/arithmetic/ripple_mult.py
qrisp/alg_primitives/arithmetic/uint_clifford_t_comparisons.py
qrisp/alg_primitives/arithmetic/adders/__init__.py
qrisp/alg_primitives/arithmetic/adders/adder_tools.py
qrisp/alg_primitives/arithmetic/adders/cuccaro.py
qrisp/alg_primitives/arithmetic/adders/fourier_adder.py
qrisp/alg_primitives/arithmetic/adders/incrementation.py
qrisp/alg_primitives/arithmetic/adders/remaud.py
qrisp/alg_primitives/arithmetic/adders/ripple_carry_adder.py
qrisp/alg_primitives/arithmetic/adders/gidney/__init__.py
qrisp/alg_primitives/arithmetic/adders/gidney/cq_gidney_adder.py
qrisp/alg_primitives/arithmetic/adders/gidney/gidney_adder.py
qrisp/alg_primitives/arithmetic/adders/gidney/qq_gidney_adder.py
qrisp/alg_primitives/arithmetic/adders/qcla/__init__.py
qrisp/alg_primitives/arithmetic/adders/qcla/wrapper_function.py
qrisp/alg_primitives/arithmetic/adders/qcla/classical_quantum/__init__.py
qrisp/alg_primitives/arithmetic/adders/qcla/classical_quantum/cq_carry_path.py
qrisp/alg_primitives/arithmetic/adders/qcla/classical_quantum/cq_qcla_adder.py
qrisp-0.7.19.dist-info/licenses/LICENSE
qrisp-0.7.19.dist-info/METADATA
qrisp-0.7.19.dist-info/WHEEL
qrisp-0.7.19.dist-info/top_level.txt
qrisp-0.7.19.dist-info/RECORD
