Metadata-Version: 2.4
Name: qrisp
Version: 0.7.19
Summary: Qrisp - A high level language for gate-based quantum computing
Home-page: https://github.com/eclipse-qrisp/Qrisp
Author: The Qrisp team
Author-email: raphael.seidel@fokus.fraunhofer.de
Project-URL: Bug Tracker, https://github.com/eclipse-qrisp/Qrisp/issues
Classifier: Programming Language :: Python :: 3
Classifier: License :: OSI Approved :: Eclipse Public License 2.0 (EPL-2.0)
Classifier: Operating System :: OS Independent
Requires-Python: >=3.10
License-File: LICENSE
Requires-Dist: numpy>=2.0
Requires-Dist: sympy<=1.13
Requires-Dist: qiskit>=0.44.0
Requires-Dist: matplotlib>=3.5.1
Requires-Dist: scipy>=1.10.0
Requires-Dist: numba
Requires-Dist: networkx
Requires-Dist: tqdm
Requires-Dist: dill
Requires-Dist: flask<2.3.0
Requires-Dist: waitress
Requires-Dist: pyyaml
Requires-Dist: requests
Requires-Dist: psutil
Requires-Dist: jax==0.7.1
Requires-Dist: jaxlib==0.7.1
Provides-Extra: iqm
Requires-Dist: iqm-client[qiskit]; extra == "iqm"
Dynamic: author
Dynamic: author-email
Dynamic: classifier
Dynamic: description
Dynamic: description-content-type
Dynamic: license-file
Dynamic: provides-extra
Dynamic: requires-dist
Dynamic: requires-python
Dynamic: summary
